edai/__init__.py
edai/__main__.py
edai/cli.py
edai/edai.py
edai/testing.py
edai-0.0.1.dist-info/METADATA
edai-0.0.1.dist-info/WHEEL
edai-0.0.1.dist-info/entry_points.txt
edai-0.0.1.dist-info/licenses/LICENSE
edai-0.0.1.dist-info/RECORD
